bds_courseware/__init__.py
bds_courseware/const.py
bds_courseware/utils.py
bds_courseware-1.1.2.dist-info/METADATA
bds_courseware-1.1.2.dist-info/WHEEL
bds_courseware-1.1.2.dist-info/top_level.txt
bds_courseware-1.1.2.dist-info/RECORD
