Metadata-Version: 2.1
Name: bds-courseware
Version: 1.1.2
Summary: Dataset utilities for EPAM Data Science basic course
Home-page: UNKNOWN
Author: UNKNOWN
Author-email: UNKNOWN
License: UNKNOWN
Platform: UNKNOWN
Requires-Dist: pandas (>=1.0.5)
Requires-Dist: gdown
